mindm/__init__.py
mindm/mindmanager.py
mindm/mindmanager_mac.py
mindm/mindmanager_mac_as.py
mindm/mindmanager_win.py
mindm/as/read.scpt
mindm/as/write.scpt
mindm-0.0.5.4.dist-info/licenses/LICENSE
mindmap/__init__.py
mindmap/export.py
mindmap/helpers.py
mindmap/import.py
mindmap/mindmap.py
mindmap/serialization.py
mindm-0.0.5.4.dist-info/METADATA
mindm-0.0.5.4.dist-info/WHEEL
mindm-0.0.5.4.dist-info/top_level.txt
mindm-0.0.5.4.dist-info/RECORD
