Metadata-Version: 2.4
Name: mindm
Version: 0.0.5.4
Summary: Python library for interacting with local installed MindManager(tm) on Windows and MacOS platform.
Author: Robert Zaufall
License: MIT
Project-URL: Homepage, https://github.com/robertZaufall/mindm
Project-URL: Issues, https://github.com/robertZaufall/mindm/issues
Classifier: Programming Language :: Python :: 3
Classifier: Operating System :: Microsoft :: Windows
Classifier: Operating System :: MacOS :: MacOS X
Requires-Python: >=3.9
License-File: LICENSE
Requires-Dist: pywin32; platform_system == "Windows"
Requires-Dist: appscript; sys_platform == "darwin"
Requires-Dist: regex
Requires-Dist: html2text
Requires-Dist: markdown
Provides-Extra: dev
Requires-Dist: pytest>=7.0; extra == "dev"
Requires-Dist: black; extra == "dev"
Requires-Dist: flake8; extra == "dev"
Requires-Dist: gitingest; extra == "dev"
Provides-Extra: docs
Requires-Dist: furo; extra == "docs"
Requires-Dist: sphinx; extra == "docs"
Requires-Dist: sphinx-pyproject; extra == "docs"
Requires-Dist: sphinx.ext.autodoc; extra == "docs"
Requires-Dist: sphinx.ext.napoleon; extra == "docs"
Requires-Dist: sphinx.ext.autosummary; extra == "docs"
Requires-Dist: gitingest; extra == "docs"
Dynamic: license-file
